LICENSE.txt
MANIFEST.in
README.rst
setup.py
django_mariposa/__init__.py
django_mariposa/models.py
django_mariposa/tests.py
django_mariposa.egg-info/PKG-INFO
django_mariposa.egg-info/SOURCES.txt
django_mariposa.egg-info/dependency_links.txt
django_mariposa.egg-info/not-zip-safe
django_mariposa.egg-info/requires.txt
django_mariposa.egg-info/top_level.txt
django_mariposa/management/__init__.py
django_mariposa/management/commands/__init__.py
django_mariposa/management/commands/migrate.py