Metadata-Version: 1.0
Name: django-mariposa
Version: 0.1
Summary: django-mariposa
Home-page: http://github.com/skyl/django-mariposa
Author: Skylar Saveland
Author-email: skylar.saveland@gmail.com
License: MIT
Keywords: python
Platform: UNKNOWN
Classifier: Programming Language :: Python
Classifier: Topic :: Software Development :: Libraries :: Python Modules
